vespucci/__init__.py
vespucci/base.py
vespucci/crawler.py
vespucci/oracle.py
vespucci/store.py
vespucci/store_stream.py
vespucci/token_bucket.py
vespucci/utils.py
vespucci-0.7.1.data/data/VERSION
vespucci-0.7.1.dist-info/METADATA
vespucci-0.7.1.dist-info/WHEEL
vespucci-0.7.1.dist-info/top_level.txt
vespucci-0.7.1.dist-info/RECORD
